main.py
setup.py
GiantMIDI_Piano.egg-info/PKG-INFO
GiantMIDI_Piano.egg-info/SOURCES.txt
GiantMIDI_Piano.egg-info/dependency_links.txt
GiantMIDI_Piano.egg-info/requires.txt
GiantMIDI_Piano.egg-info/top_level.txt