Metadata-Version: 2.1
Name: GiantMIDI-Piano
Version: 912.6
Summary: x
Author: 123
Author-email: xxx@outlook.com
Requires-Dist: requests
